quality_toolkit/__init__.py
quality_toolkit/helpers/__init__.py
quality_toolkit/helpers/api_functions.py
quality_toolkit/helpers/local_functions.py
quality_toolkit/helpers/ui_functions.py
quality_toolkit/services/__init__.py
quality_toolkit/services/base_sql.py
quality_toolkit/services/mssql.py
quality_toolkit/services/psql.py
quality_toolkit/services/sftp.py
quality_toolkit/services/sso.py
quality_toolkit-2.5.6.dist-info/licenses/LICENSE
quality_toolkit-2.5.6.dist-info/METADATA
quality_toolkit-2.5.6.dist-info/WHEEL
quality_toolkit-2.5.6.dist-info/top_level.txt
quality_toolkit-2.5.6.dist-info/RECORD
