Metadata-Version: 2.4
Name: quality-toolkit
Version: 2.5.6
Summary: Toolkit for the quality in order to help writing tests
Author-email: VpTech <vptech@veepee.com>
Project-URL: Homepage, https://github.com/veepee-oss/quality-toolkit
Keywords: Quality,Toolkit,Testing
Requires-Python: >=3.10
License-File: LICENSE
Requires-Dist: psycopg2-binary==2.9.11
Requires-Dist: requests==2.32.5
Requires-Dist: pytz==2025.2
Requires-Dist: python-tds==1.17.1
Requires-Dist: selenium==4.36.0
Requires-Dist: python-keycloak-client==0.2.3
Requires-Dist: pysftp==0.2.9
Requires-Dist: playwright==1.55.0
Dynamic: license-file
